sphinxcontrib_thm-1.3.dev20210214-py3.9-nspkg.pth
sphinxcontrib/thm.py
sphinxcontrib_thm-1.3.dev20210214.dist-info/LICENSE
sphinxcontrib_thm-1.3.dev20210214.dist-info/METADATA
sphinxcontrib_thm-1.3.dev20210214.dist-info/WHEEL
sphinxcontrib_thm-1.3.dev20210214.dist-info/namespace_packages.txt
sphinxcontrib_thm-1.3.dev20210214.dist-info/top_level.txt
sphinxcontrib_thm-1.3.dev20210214.dist-info/RECORD
