Metadata-Version: 2.1
Name: sphinxcontrib-thm
Version: 1.3.dev20210214
Summary: Sphinx extension for directives mentioned in amsthm (theorem, example, exercise,...) and more
Home-page: https://github.com/rpuntaie/sphinxcontrib-thm
Author: Marcin Szamotulski, Roland Puntaier
Author-email: coot@riseup.net, roland.puntaier@gmail.com
License: BSD
Download-URL: http://pypi.python.org/pypi/sphinxcontrib-thm
Platform: any
Classifier: Development Status :: 4 - Beta
Classifier: Environment :: Console
Classifier: Environment :: Web Environment
Classifier: Intended Audience :: Developers
Classifier: License :: OSI Approved :: BSD License
Classifier: Operating System :: OS Independent
Classifier: Programming Language :: Python
Classifier: Programming Language :: Python :: 2.7
Classifier: Programming Language :: Python :: 3.5
Classifier: Topic :: Documentation
Classifier: Topic :: Utilities
Requires-Dist: Sphinx
